moad/__init__.py
moad/__main__.py
moad/moad.py
moad-0.3.0.dist-info/LICENSE
moad-0.3.0.dist-info/METADATA
moad-0.3.0.dist-info/WHEEL
moad-0.3.0.dist-info/top_level.txt
moad-0.3.0.dist-info/RECORD
