Metadata-Version: 2.1
Name: moad
Version: 0.3.0
Summary: Mic open API docs
Home-page: https://github.com/claasd/moad
Author: Claas Diederichs
Author-email: 
License: MIT
Platform: UNKNOWN
Classifier: Programming Language :: Python :: 3.6
Classifier: Programming Language :: Python :: 3.7
Classifier: Programming Language :: Python :: 3.8
Classifier: Programming Language :: Python :: 3.9
Classifier: License :: OSI Approved :: MIT License
Classifier: Operating System :: OS Independent
Requires-Python: >=3.6
License-File: LICENSE
Requires-Dist: PyYaml
